[
  {
    "__type__": "cc.Prefab",
    "_name": "",
    "_objFlags": 0,
    "_native": "",
    "data": {
      "__id__": 1
    },
    "optimizationPolicy": 0,
    "persistent": false
  },
  {
    "__type__": "cc.Node",
    "_name": "Bot",
    "_objFlags": 0,
    "_parent": null,
    "_children": [
      {
        "__id__": 2
      },
      {
        "__id__": 7
      }
    ],
    "_active": true,
    "_components": [
      {
        "__id__": 27
      }
    ],
    "_prefab": {
      "__id__": 29
    },
    "_lpos": {
      "__type__": "cc.Vec3",
      "x": 0,
      "y": 0,
      "z": 0
    },
    "_lrot": {
      "__type__": "cc.Quat",
      "x": 0,
      "y": 0,
      "z": 0,
      "w": 1
    },
    "_lscale": {
      "__type__": "cc.Vec3",
      "x": 1,
      "y": 1,
      "z": 1
    },
    "_layer": 1073741824,
    "_euler": {
      "__type__": "cc.Vec3",
      "x": 0,
      "y": 0,
      "z": 0
    },
    "_id": ""
  },
  {
    "__type__": "cc.Node",
    "_name": "Cube",
    "_objFlags": 0,
    "_parent": {
      "__id__": 1
    },
    "_children": [],
    "_active": true,
    "_components": [
      {
        "__id__": 3
      }
    ],
    "_prefab": {
      "__id__": 6
    },
    "_lpos": {
      "__type__": "cc.Vec3",
      "x": -1.4901161193847656e-8,
      "y": 0,
      "z": 0
    },
    "_lrot": {
      "__type__": "cc.Quat",
      "x": -0.7071068407911908,
      "y": 0,
      "z": 0,
      "w": 0.7071067215818992
    },
    "_lscale": {
      "__type__": "cc.Vec3",
      "x": 100,
      "y": 100,
      "z": 100
    },
    "_layer": 1073741824,
    "_euler": {
      "__type__": "cc.Vec3",
      "x": -90.00000965934633,
      "y": 0,
      "z": 0
    },
    "_id": ""
  },
  {
    "__type__": "cc.SkinnedMeshRenderer",
    "_name": "",
    "_objFlags": 0,
    "node": {
      "__id__": 2
    },
    "_enabled": true,
    "__prefab": {
      "__id__": 4
    },
    "_materials": [
      {
        "__uuid__": "bbb36ea6-a98e-409f-be2b-029b3c8d2782@aaacc",
        "__expectedType__": "cc.Material"
      }
    ],
    "_visFlags": 0,
    "lightmapSettings": {
      "__id__": 5
    },
    "_mesh": {
      "__uuid__": "bbb36ea6-a98e-409f-be2b-029b3c8d2782@2f6d1",
      "__expectedType__": "cc.Mesh"
    },
    "_shadowCastingMode": 0,
    "_shadowReceivingMode": 1,
    "_shadowBias": 0,
    "_shadowNormalBias": 0,
    "_enableMorph": true,
    "_skeleton": {
      "__uuid__": "bbb36ea6-a98e-409f-be2b-029b3c8d2782@438fe",
      "__expectedType__": "cc.Skeleton"
    },
    "_skinningRoot": {
      "__id__": 1
    },
    "_id": ""
  },
  {
    "__type__": "cc.CompPrefabInfo",
    "fileId": "7bvyu9DbtaDYd5+U2pyXWz"
  },
  {
    "__type__": "cc.ModelLightmapSettings",
    "texture": null,
    "uvParam": {
      "__type__": "cc.Vec4",
      "x": 0,
      "y": 0,
      "z": 0,
      "w": 0
    },
    "_bakeable": false,
    "_castShadow": false,
    "_receiveShadow": false,
    "_recieveShadow": false,
    "_lightmapSize": 64
  },
  {
    "__type__": "cc.PrefabInfo",
    "root": {
      "__id__": 1
    },
    "asset": {
      "__id__": 0
    },
    "fileId": "505MQWj+JYloYAfGjasX27"
  },
  {
    "__type__": "cc.Node",
    "_name": "Armature",
    "_objFlags": 0,
    "_parent": {
      "__id__": 1
    },
    "_children": [
      {
        "__id__": 8
      }
    ],
    "_active": true,
    "_components": [],
    "_prefab": {
      "__id__": 26
    },
    "_lpos": {
      "__type__": "cc.Vec3",
      "x": -0.09456926584243774,
      "y": 1.5146827697753906,
      "z": -0.03971505165100098
    },
    "_lrot": {
      "__type__": "cc.Quat",
      "x": -0.7071068407911908,
      "y": 0,
      "z": 0,
      "w": 0.7071067215818992
    },
    "_lscale": {
      "__type__": "cc.Vec3",
      "x": 165.37753295898438,
      "y": 165.37753295898438,
      "z": 165.37753295898438
    },
    "_layer": 1073741824,
    "_euler": {
      "__type__": "cc.Vec3",
      "x": -90.00000965934633,
      "y": 0,
      "z": 0
    },
    "_id": ""
  },
  {
    "__type__": "cc.Node",
    "_name": "Bone",
    "_objFlags": 0,
    "_parent": {
      "__id__": 7
    },
    "_children": [
      {
        "__id__": 9
      },
      {
        "__id__": 15
      },
      {
        "__id__": 21
      }
    ],
    "_active": true,
    "_components": [],
    "_prefab": {
      "__id__": 25
    },
    "_lpos": {
      "__type__": "cc.Vec3",
      "x": 0.00019834309932775795,
      "y": 0.00008256686851382256,
      "z": -0.00010725745960371569
    },
    "_lrot": {
      "__type__": "cc.Quat",
      "x": 0.7049517074568671,
      "y": 0.05516421080417771,
      "z": -0.05516421080417771,
      "w": 0.7049517074568671
    },
    "_lscale": {
      "__type__": "cc.Vec3",
      "x": 1,
      "y": 1,
      "z": 1
    },
    "_layer": 1073741824,
    "_euler": {
      "__type__": "cc.Vec3",
      "x": 90.00000000000001,
      "y": 8.948836103904314,
      "z": 0
    },
    "_id": ""
  },
  {
    "__type__": "cc.Node",
    "_name": "Bone.001",
    "_objFlags": 0,
    "_parent": {
      "__id__": 8
    },
    "_children": [
      {
        "__id__": 10
      }
    ],
    "_active": true,
    "_components": [],
    "_prefab": {
      "__id__": 14
    },
    "_lpos": {
      "__type__": "cc.Vec3",
      "x": -0.00025009532691910863,
      "y": 0.009195761755108833,
      "z": 0.010972200892865658
    },
    "_lrot": {
      "__type__": "cc.Quat",
      "x": 6.869421320751236e-8,
      "y": 4.9699032606271e-8,
      "z": -0.8101944949690444,
      "w": 0.5861611385291999
    },
    "_lscale": {
      "__type__": "cc.Vec3",
      "x": 1,
      "y": 1,
      "z": 1
    },
    "_layer": 1073741824,
    "_euler": {
      "__type__": "cc.Vec3",
      "x": 179.99997050074174,
      "y": 179.9999689419072,
      "z": -71.77012309141436
    },
    "_id": ""
  },
  {
    "__type__": "cc.Node",
    "_name": "Bone.002",
    "_objFlags": 0,
    "_parent": {
      "__id__": 9
    },
    "_children": [
      {
        "__id__": 11
      }
    ],
    "_active": true,
    "_components": [],
    "_prefab": {
      "__id__": 13
    },
    "_lpos": {
      "__type__": "cc.Vec3",
      "x": -5.846644002271972e-11,
      "y": 0.00958293117582798,
      "z": -2.749248328992593e-10
    },
    "_lrot": {
      "__type__": "cc.Quat",
      "x": -1.9176295645184765e-8,
      "y": 3.6684734366850822e-9,
      "z": 0.11067560048831127,
      "w": 0.9938565849540623
    },
    "_lscale": {
      "__type__": "cc.Vec3",
      "x": 1,
      "y": 1,
      "z": 1
    },
    "_layer": 1073741824,
    "_euler": {
      "__type__": "cc.Vec3",
      "x": -0.0000022864818314973937,
      "y": 6.775965971926728e-7,
      "z": 12.708524861334306
    },
    "_id": ""
  },
  {
    "__type__": "cc.Node",
    "_name": "Bone.002_end",
    "_objFlags": 0,
    "_parent": {
      "__id__": 10
    },
    "_children": [],
    "_active": true,
    "_components": [],
    "_prefab": {
      "__id__": 12
    },
    "_lpos": {
      "__type__": "cc.Vec3",
      "x": -2.2204459996194763e-18,
      "y": 0.00904181320220232,
      "z": 0
    },
    "_lrot": {
      "__type__": "cc.Quat",
      "x": 0,
      "y": 0,
      "z": 0,
      "w": 1
    },
    "_lscale": {
      "__type__": "cc.Vec3",
      "x": 1,
      "y": 1,
      "z": 1
    },
    "_layer": 1073741824,
    "_euler": {
      "__type__": "cc.Vec3",
      "x": 0,
      "y": 0,
      "z": 0
    },
    "_id": ""
  },
  {
    "__type__": "cc.PrefabInfo",
    "root": {
      "__id__": 1
    },
    "asset": {
      "__id__": 0
    },
    "fileId": "b2A7JNzf9Zjrf0hmhVF0Vh"
  },
  {
    "__type__": "cc.PrefabInfo",
    "root": {
      "__id__": 1
    },
    "asset": {
      "__id__": 0
    },
    "fileId": "49Rpg5OilZepBMOCL6VHb9"
  },
  {
    "__type__": "cc.PrefabInfo",
    "root": {
      "__id__": 1
    },
    "asset": {
      "__id__": 0
    },
    "fileId": "39jDCffXhSrYRbvOy5tg1s"
  },
  {
    "__type__": "cc.Node",
    "_name": "Bone.003",
    "_objFlags": 0,
    "_parent": {
      "__id__": 8
    },
    "_children": [
      {
        "__id__": 16
      }
    ],
    "_active": true,
    "_components": [],
    "_prefab": {
      "__id__": 20
    },
    "_lpos": {
      "__type__": "cc.Vec3",
      "x": -0.00025009369710460305,
      "y": 0.009195760823786259,
      "z": -0.009781521745026112
    },
    "_lrot": {
      "__type__": "cc.Quat",
      "x": 5.862419116564334e-8,
      "y": 6.12543325785998e-8,
      "z": -0.6914262705833925,
      "w": 0.7224470308244987
    },
    "_lscale": {
      "__type__": "cc.Vec3",
      "x": 1.0000001192092896,
      "y": 1.0000001192092896,
      "z": 1
    },
    "_layer": 1073741824,
    "_euler": {
      "__type__": "cc.Vec3",
      "x": 0.0002213107319296215,
      "y": 0.00022152389954843864,
      "z": -87.48623369936962
    },
    "_id": ""
  },
  {
    "__type__": "cc.Node",
    "_name": "Bone.004",
    "_objFlags": 0,
    "_parent": {
      "__id__": 15
    },
    "_children": [
      {
        "__id__": 17
      }
    ],
    "_active": true,
    "_components": [],
    "_prefab": {
      "__id__": 19
    },
    "_lpos": {
      "__type__": "cc.Vec3",
      "x": -4.093422129036739e-11,
      "y": 0.00958293117582798,
      "z": 2.427160417095564e-10
    },
    "_lrot": {
      "__type__": "cc.Quat",
      "x": -5.9811460911699555e-9,
      "y": -1.1482277944111274e-7,
      "z": 0.11067561520694573,
      "w": 0.9938565833149926
    },
    "_lscale": {
      "__type__": "cc.Vec3",
      "x": 1,
      "y": 1,
      "z": 1
    },
    "_layer": 1073741824,
    "_euler": {
      "__type__": "cc.Vec3",
      "x": 7.945250961319467e-7,
      "y": -0.000013327532446890461,
      "z": 12.708526558391307
    },
    "_id": ""
  },
  {
    "__type__": "cc.Node",
    "_name": "Bone.004_end",
    "_objFlags": 0,
    "_parent": {
      "__id__": 16
    },
    "_children": [],
    "_active": true,
    "_components": [],
    "_prefab": {
      "__id__": 18
    },
    "_lpos": {
      "__type__": "cc.Vec3",
      "x": 0,
      "y": 0.00904181320220232,
      "z": 0
    },
    "_lrot": {
      "__type__": "cc.Quat",
      "x": 0,
      "y": 0,
      "z": 0,
      "w": 1
    },
    "_lscale": {
      "__type__": "cc.Vec3",
      "x": 1,
      "y": 1,
      "z": 1
    },
    "_layer": 1073741824,
    "_euler": {
      "__type__": "cc.Vec3",
      "x": 0,
      "y": 0,
      "z": 0
    },
    "_id": ""
  },
  {
    "__type__": "cc.PrefabInfo",
    "root": {
      "__id__": 1
    },
    "asset": {
      "__id__": 0
    },
    "fileId": "a3tY6XDzJfEJi2qvjwQIwS"
  },
  {
    "__type__": "cc.PrefabInfo",
    "root": {
      "__id__": 1
    },
    "asset": {
      "__id__": 0
    },
    "fileId": "71BTJykqhVFJn47JlBp4Vp"
  },
  {
    "__type__": "cc.PrefabInfo",
    "root": {
      "__id__": 1
    },
    "asset": {
      "__id__": 0
    },
    "fileId": "2fSPnvEzhfcIhg3oAkwebC"
  },
  {
    "__type__": "cc.Node",
    "_name": "Bone.005",
    "_objFlags": 0,
    "_parent": {
      "__id__": 8
    },
    "_children": [
      {
        "__id__": 22
      }
    ],
    "_active": true,
    "_components": [],
    "_prefab": {
      "__id__": 24
    },
    "_lpos": {
      "__type__": "cc.Vec3",
      "x": -0.002629628172144294,
      "y": 0.02180137112736702,
      "z": -0.0000057145020946336444
    },
    "_lrot": {
      "__type__": "cc.Quat",
      "x": -6.8479842172204e-8,
      "y": -5.185949797694227e-8,
      "z": -0.7971995464872285,
      "w": 0.6037158959979024
    },
    "_lscale": {
      "__type__": "cc.Vec3",
      "x": 1,
      "y": 1,
      "z": 1
    },
    "_layer": 1073741824,
    "_euler": {
      "__type__": "cc.Vec3",
      "x": -179.99996504399564,
      "y": -179.99996368449092,
      "z": -74.27299046853827
    },
    "_id": ""
  },
  {
    "__type__": "cc.Node",
    "_name": "Bone.005_end",
    "_objFlags": 0,
    "_parent": {
      "__id__": 21
    },
    "_children": [],
    "_active": true,
    "_components": [],
    "_prefab": {
      "__id__": 23
    },
    "_lpos": {
      "__type__": "cc.Vec3",
      "x": 4.440891999238953e-18,
      "y": 0.006176137365400791,
      "z": 0
    },
    "_lrot": {
      "__type__": "cc.Quat",
      "x": 0,
      "y": 0,
      "z": 0,
      "w": 1
    },
    "_lscale": {
      "__type__": "cc.Vec3",
      "x": 1,
      "y": 1,
      "z": 1
    },
    "_layer": 1073741824,
    "_euler": {
      "__type__": "cc.Vec3",
      "x": 0,
      "y": 0,
      "z": 0
    },
    "_id": ""
  },
  {
    "__type__": "cc.PrefabInfo",
    "root": {
      "__id__": 1
    },
    "asset": {
      "__id__": 0
    },
    "fileId": "35OSKWLnZZ4aEpqE0SXoJE"
  },
  {
    "__type__": "cc.PrefabInfo",
    "root": {
      "__id__": 1
    },
    "asset": {
      "__id__": 0
    },
    "fileId": "827jI2hLpSlY2jPt/GjB73"
  },
  {
    "__type__": "cc.PrefabInfo",
    "root": {
      "__id__": 1
    },
    "asset": {
      "__id__": 0
    },
    "fileId": "5519WvPR5YZaKa2a8mndFb"
  },
  {
    "__type__": "cc.PrefabInfo",
    "root": {
      "__id__": 1
    },
    "asset": {
      "__id__": 0
    },
    "fileId": "14hiJtlJ9Qk4osj7+BJ6ZV"
  },
  {
    "__type__": "cc.SkeletalAnimation",
    "_name": "",
    "_objFlags": 0,
    "node": {
      "__id__": 1
    },
    "_enabled": true,
    "__prefab": {
      "__id__": 28
    },
    "playOnLoad": false,
    "_clips": [
      {
        "__uuid__": "bbb36ea6-a98e-409f-be2b-029b3c8d2782@83fcf",
        "__expectedType__": "cc.AnimationClip"
      },
      {
        "__uuid__": "bbb36ea6-a98e-409f-be2b-029b3c8d2782@4837e",
        "__expectedType__": "cc.AnimationClip"
      },
      {
        "__uuid__": "bbb36ea6-a98e-409f-be2b-029b3c8d2782@e682c",
        "__expectedType__": "cc.AnimationClip"
      },
      {
        "__uuid__": "bbb36ea6-a98e-409f-be2b-029b3c8d2782@97e42",
        "__expectedType__": "cc.AnimationClip"
      }
    ],
    "_defaultClip": {
      "__uuid__": "bbb36ea6-a98e-409f-be2b-029b3c8d2782@83fcf",
      "__expectedType__": "cc.AnimationClip"
    },
    "_useBakedAnimation": true,
    "_sockets": [],
    "_id": ""
  },
  {
    "__type__": "cc.CompPrefabInfo",
    "fileId": "ecfo2bPhhRG5/q7GgZhNV9"
  },
  {
    "__type__": "cc.PrefabInfo",
    "root": {
      "__id__": 1
    },
    "asset": {
      "__id__": 0
    },
    "fileId": "921WzJHudRXr5OKnHSoNRH"
  }
]